README.md
setup.py
ProstateNetLoaders/ExecuteLoader.py
ProstateNetLoaders/LookUpTable.py
ProstateNetLoaders/SegmentationLoaders.py
ProstateNetLoaders/SeriesPathLoaders.py
ProstateNetLoaders/SitkOperations.py
ProstateNetLoaders/__init__.py
ProstateNetLoaders.egg-info/PKG-INFO
ProstateNetLoaders.egg-info/SOURCES.txt
ProstateNetLoaders.egg-info/dependency_links.txt
ProstateNetLoaders.egg-info/top_level.txt