Metadata-Version: 2.1
Name: ProstateNetLoaders
Version: 0.0.1
Summary: Prostate Net loading functions
Home-page: https://github.com/dzaridis/ProstateNetLoading
Author: Dimitris Zaridis
Author-email: dimzaridis@email.com
License: UNKNOWN
Platform: UNKNOWN
Classifier: Programming Language :: Python :: 3
Classifier: License :: OSI Approved :: MIT License
Classifier: Operating System :: OS Independent
